timescaler/__init__.py
timescaler/constants.py
timescaler/decorator.py
timescaler/logger.py
timescaler/main.py
timescaler-0.1.0.dist-info/METADATA
timescaler-0.1.0.dist-info/WHEEL
timescaler-0.1.0.dist-info/top_level.txt
timescaler-0.1.0.dist-info/RECORD
