Metadata-Version: 2.4
Name: timescaler
Version: 0.1.0
Summary: Monitor your timescaledb like a pro
Author: Abhishek Mittal
Requires-Python: >=3.8
Requires-Dist: python-dotenv
Requires-Dist: psycopg2-binary
Requires-Dist: python-logging-loki
